emcie/sdk/__init__.py
emcie/sdk/py.typed
emcie_sdk-0.1.0.dist-info/METADATA
emcie_sdk-0.1.0.dist-info/WHEEL
emcie_sdk-0.1.0.dist-info/RECORD
